nonebot_plugin_word_censor/__init__.py
nonebot_plugin_word_censor/config.py
nonebot_plugin_word_censor-0.3.1.dist-info/licenses/LICENSE
nonebot_plugin_word_censor-0.3.1.dist-info/METADATA
nonebot_plugin_word_censor-0.3.1.dist-info/WHEEL
nonebot_plugin_word_censor-0.3.1.dist-info/RECORD
