Metadata-Version: 2.4
Name: nonebot-plugin-word-censor
Version: 0.3.1
Summary: 一个用于拦截 Bot 发送包含敏感词或正则匹配内容的消息审查插件
License: MIT
License-File: LICENSE
Keywords: nonebot,nonebot2,plugin,censor,filter
Author: ChlorophyTeio
Author-email: chlorophyimo@gmail.com
Requires-Python: >=3.8,<4.0
Classifier: License :: OSI Approved :: MIT License
Classifier: Programming Language :: Python :: 3
Classifier: Programming Language :: Python :: 3.8
Classifier: Programming Language :: Python :: 3.9
Classifier: Programming Language :: Python :: 3.10
Classifier: Programming Language :: Python :: 3.11
Classifier: Programming Language :: Python :: 3.12
Classifier: Programming Language :: Python :: 3.13
Classifier: Programming Language :: Python :: 3.14
Requires-Dist: nonebot-plugin-localstore (>=0.7.1,<0.8.0)
Requires-Dist: nonebot2 (>=2.3.0,<3.0.0)
Requires-Dist: pydantic (>=1.10.0,<3.0.0)
Project-URL: Homepage, https://github.com/ChlorophyTeio/nonebot-plugin-word-censor
Project-URL: Repository, https://github.com/ChlorophyTeio/nonebot-plugin-word-censor
